backtrader_plotly/__init__.py
backtrader_plotly/plotter.py
backtrader_plotly/scheme.py
backtrader_plotly-1.5.0.dist-info/LICENSE
backtrader_plotly-1.5.0.dist-info/METADATA
backtrader_plotly-1.5.0.dist-info/WHEEL
backtrader_plotly-1.5.0.dist-info/top_level.txt
backtrader_plotly-1.5.0.dist-info/RECORD
