Metadata-Version: 2.1
Name: backtrader-plotly
Version: 1.5.0
Summary: Library replacing original matlibplot used by backtrader
Home-page: https://github.com/lamkashingpaul/backtrader_plotly
Author: Paul Lam
Author-email: lamkashingpaul@gmail.com
License: GPLv3
Project-URL: Bug Tracker, https://github.com/lamkashingpaul/backtrader_plotly/issues
Classifier: Programming Language :: Python :: 3
Classifier: License :: OSI Approved :: GNU General Public License v3 (GPLv3)
Classifier: Operating System :: OS Independent
Requires-Python: >=3.8
License-File: LICENSE
